lottokit/__init__.py
lottokit/daletou.py
lottokit/utils/__init__.py
lottokit/utils/analyze_util.py
lottokit/utils/calculate_util.py
lottokit/utils/denoiser_util.py
lottokit/utils/genetics_util.py
lottokit/utils/io_util.py
lottokit/utils/model_util.py
lottokit/utils/spider_util.py
lottokit-2.0.dist-info/LICENSE
lottokit-2.0.dist-info/METADATA
lottokit-2.0.dist-info/WHEEL
lottokit-2.0.dist-info/top_level.txt
lottokit-2.0.dist-info/RECORD
