Metadata-Version: 2.1
Name: lottokit
Version: 2.0
Summary: Lotto Kit Package
Author: nickdecodes
Author-email: nickdecodes <nickdecodes@163.com>
License: Apache License
Project-URL: Documentation, http://python-lottokit.readthedocs.io
Project-URL: Source, https://github.com/nickdecodes/python-lottokit
Keywords: lottokit,lottery
Requires-Python: >=3.9
License-File: LICENSE
Requires-Dist: selenium >=4.11.2
Requires-Dist: webdriver-manager >=4.0.0
Requires-Dist: pandas >=2.0.3
Requires-Dist: numpy >=1.24.3
Requires-Dist: statsmodels >=0.14.0
Requires-Dist: Pillow >=9.5.0
Requires-Dist: scikit-learn >=1.3.2
Requires-Dist: pmdarima >=2.0.4
Requires-Dist: pywavelets >=1.6.0
Requires-Dist: requests
Requires-Dist: twine >=4.0.2
Requires-Dist: build >=1.2.1
Requires-Dist: installer >=0.7.0
